LICENSE
MANIFEST.in
README.md
setup.py
simple_draw.py
simple_draw.egg-info/PKG-INFO
simple_draw.egg-info/SOURCES.txt
simple_draw.egg-info/dependency_links.txt
simple_draw.egg-info/requires.txt
simple_draw.egg-info/top_level.txt